ask_ron/__init__.py
ask_ron/ask.py
ask_ron-1.0.0.dist-info/METADATA
ask_ron-1.0.0.dist-info/WHEEL
ask_ron-1.0.0.dist-info/entry_points.txt
ask_ron-1.0.0.dist-info/top_level.txt
ask_ron-1.0.0.dist-info/RECORD
