Metadata-Version: 2.1
Name: ask-ron
Version: 1.0.0
Summary: A basic 8 ball library that generates random output
Home-page: https://github.com/nairraghav/ron-cipher
Author: Raghav Nair
Author-email: nairraghav@hotmail.com
License: UNKNOWN
Platform: UNKNOWN
Classifier: Programming Language :: Python :: 3
Classifier: License :: OSI Approved :: MIT License
Classifier: Operating System :: OS Independent
Requires-Python: >=3
